fastSum/__init__.py
fastsum-0.0.1.dist-info/LICENSE
fastsum-0.0.1.dist-info/METADATA
fastsum-0.0.1.dist-info/WHEEL
fastsum-0.0.1.dist-info/top_level.txt
fastsum-0.0.1.dist-info/RECORD
