Metadata-Version: 2.1
Name: fastsum
Version: 0.0.1
Summary: fastNLP for summarization
Home-page: https://github.com/fastnlp/fastsum
Author: FudanNLP
License: Apache License
Platform: UNKNOWN
Requires-Python: >=3.6
Requires-Dist: fastNLP (>=0.5.5)
